{
  "db_name": "PostgreSQL",
  "query": "SELECT id, user_id, workshop_id, rating, title, content, status::text as \"status!\", created_at, updated_at\n               FROM reviews WHERE id = $1",
  "describe": {
    "columns": [
      {
        "ordinal": 0,
        "name": "id",
        "type_info": "Uuid"
      },
      {
        "ordinal": 1,
        "name": "user_id",
        "type_info": "Uuid"
      },
      {
        "ordinal": 2,
        "name": "workshop_id",
        "type_info": "Uuid"
      },
      {
        "ordinal": 3,
        "name": "rating",
        "type_info": "Int2"
      },
      {
        "ordinal": 4,
        "name": "title",
        "type_info": "Text"
      },
      {
        "ordinal": 5,
        "name": "content",
        "type_info": "Text"
      },
      {
        "ordinal": 6,
        "name": "status!",
        "type_info": "Text"
      },
      {
        "ordinal": 7,
        "name": "created_at",
        "type_info": "Timestamptz"
      },
      {
        "ordinal": 8,
        "name": "updated_at",
        "type_info": "Timestamptz"
      }
    ],
    "parameters": {
      "Left": [
        "Uuid"
      ]
    },
    "nullable": [
      false,
      false,
      false,
      false,
      false,
      false,
      null,
      false,
      false
    ]
  },
  "hash": "a592d5dbddfe323d3ebdd98cd051d244ee410ad6a6f9bb4331e507d491641f6e"
}
